keyhunter/__init__.py
keyhunter/__main__.py
keyhunter/keyhunter.py
keyhunter-0.1.0.dist-info/METADATA
keyhunter-0.1.0.dist-info/WHEEL
keyhunter-0.1.0.dist-info/entry_points.txt
keyhunter-0.1.0.dist-info/top_level.txt
keyhunter-0.1.0.dist-info/RECORD
