Metadata-Version: 2.4
Name: keyhunter
Version: 0.1.0
Summary: A tool to recover lost bitcoin private keys from dead hard drives.
Project-URL: Homepage, https://github.com/RecRanger/keyhunter
Project-URL: Issues, https://github.com/RecRanger/keyhunter/issues
Requires-Python: >=3.12
Requires-Dist: loguru>=0.7.3
